chkpy/__init__.py
chkpy/__main__.py
chkpy/art.py
chkpy/directory.py
chkpy/filetest copy.py
chkpy/filetest.py
chkpy/main.py
chkpy/modes.py
chkpy/test.py
chkpy-1.0.5.dist-info/LICENSE
chkpy-1.0.5.dist-info/METADATA
chkpy-1.0.5.dist-info/WHEEL
chkpy-1.0.5.dist-info/entry_points.txt
chkpy-1.0.5.dist-info/top_level.txt
chkpy-1.0.5.dist-info/RECORD
